mcp_google_sheets/__init__.py
mcp_google_sheets/server.py
mcp_gsheets_folder-0.1.0.dist-info/METADATA
mcp_gsheets_folder-0.1.0.dist-info/WHEEL
mcp_gsheets_folder-0.1.0.dist-info/entry_points.txt
mcp_gsheets_folder-0.1.0.dist-info/licenses/LICENSE
mcp_gsheets_folder-0.1.0.dist-info/RECORD
