Metadata-Version: 2.4
Name: mcp-gsheets-folder
Version: 0.1.0
Summary: This MCP server integrates with your Google Drive and Google Sheets, with folder-based access control.
Project-URL: Homepage, https://github.com/yourusername/mcp-gsheets-folder
Project-URL: Bug Tracker, https://github.com/yourusername/mcp-gsheets-folder/issues
Project-URL: Repository, https://github.com/yourusername/mcp-gsheets-folder.git
Author-email: KimJeongKyu <your-email@example.com>
License-File: LICENSE
Requires-Python: >=3.10
Requires-Dist: google-api-python-client>=2.117.0
Requires-Dist: google-auth-oauthlib>=1.2.0
Requires-Dist: google-auth>=2.28.1
Requires-Dist: mcp>=1.5.0
Requires-Dist: python-dotenv>=1.0.0
